dataporten/__init__.py
dataporten/psa.py
dataporten_auth-0.1.1.dist-info/DESCRIPTION.rst
dataporten_auth-0.1.1.dist-info/METADATA
dataporten_auth-0.1.1.dist-info/RECORD
dataporten_auth-0.1.1.dist-info/WHEEL
dataporten_auth-0.1.1.dist-info/metadata.json
dataporten_auth-0.1.1.dist-info/top_level.txt
