Metadata-Version: 2.0
Name: dataporten-auth
Version: 0.1.1
Summary: A plugin for python-social-auth to authenticate with dataporten
Home-page: https://github.com/hmpf/dataporten-auth
Author: Hanne Moa
Author-email: hanne.moa@uninett.no
License: MIT
Keywords: django,oauth2
Platform: any
Classifier: Environment :: Web Environment
Classifier: Framework :: Django
Classifier: Intended Audience :: Developers
Classifier: License :: OSI Approved :: MIT License
Classifier: Operating System :: OS Independent
Classifier: Programming Language :: Python
Classifier: Programming Language :: Python :: 2.7
Classifier: Programming Language :: Python :: 3.4
Classifier: Programming Language :: Python :: 3.5
Classifier: Framework :: Django
Classifier: Framework :: Flask
Classifier: Framework :: Pyramid
Classifier: Topic :: Internet :: WWW/HTTP
Classifier: Topic :: Software Development :: Libraries :: Python Modules
Classifier: Topic :: Utilities
Requires-Dist: python-social-auth
